Workbook
Name LecturerName: 'Выбор тем'!$B$4
Name ResponseDate: 'Выбор тем'!$F$4
Name SurveyVersion: 'Выбор тем'!$F$5
Name CompletionState: 'Выбор тем'!$B$5

Sheet Выбор тем
A1: КАКИЕ ТЕМЫ ВЫ ГОТОВЫ ЧИТАТЬ?
A2: Каталог тем · Rozum · Содержание внутри файла
A3: Укажите ФИО, откройте содержание и отметьте готовность. Заполняйте светло-зелёные ячейки.
A4: Ваше ФИО | E4: Дата анкеты
A5: Заполнение | B5: В процессе | E5: Версия | F5: ROZUM-2026-10-16-v2
A6: «Да» — готовы читать тему. При ограничениях по содержанию или программе выберите «Частично» и поясните их в комментарии.
A7: Все содержания → | D7: Инструкция →
A9: Код темы | B9: Тема | C9: В каких программах | D9: Содержание | E9: Могу читать | F9: Комментарий преподавателя
A10: T-69C6C7C7 | B10: Case Management в SOAR | C10: РКИОК | D10: Открыть →
A11: T-22B750DE | B11: DoS- и DDoS-кибератаки | C11: ТК | D11: Открыть →
A12: T-2AF2EE0F | B12: Internet of Things (IoT): архитектура, протоколы | C12: ОПКС | D12: Открыть →
A13: T-33E76F66 | B13: IP-адресация | C13: ОКМ | D13: Открыть →
A14: T-9917B01E | B14: OSINT-инструменты | C14: РКИОК | D14: Открыть →
A15: T-B82746ED | B15: SIEM: назначение, архитектура, нормализация и корреляция событий на базе Ntechnology SIEM | C15: РКИОК | D15: Открыть →
A16: T-BF0DCE22 | B16: SIEM-системы. Краткий обзор существующих решений. Сертифицированные open-source и коммерческие решения в Республике Беларусь | C16: ОКБО | D16: Открыть →
A17: T-2D7EF13A | B17: Suricata – установка, настройка, правила. Написание правил нормализации для Ntechnology SIEM (NTECH SIEM) | C17: РКИОК | D17: Открыть →
A18: T-18B4A131 | B18: Автоматизация и цифровизация административных процедур | C18: ЦТГУ | D18: Открыть →
A19: T-2C3B1F04 | B19: Автоматизация процессов обеспечения кибербезопасности с использованием систем класса SGRC | C19: ККС | D19: Открыть →
A20: T-E7C04975 | B20: Агрегация каналов и отказоустойчивость: STP, LACP, балансировка | C20: ОПКС | D20: Открыть →
A21: T-DA2CB29B | B21: Агрегация маршрутов | C21: ОКМ | D21: Открыть →
... A275: T-E90F5F72 | B275: Этапы действий ЦКБ: мониторинг, обнаружение, анализ, реагирование, восстановление | C275: ОКБО | D275: Открыть →
A277: Сохраните файл «Анкета_Фамилия.xlsx» и отправьте организатору ЛИЧНО. Других ответов преподавателей в этом файле нет.

Sheet Содержание тем
A1: СОДЕРЖАНИЕ ТЕМ
A2: Темы из УТП и программ. Ниже — фактические тексты источников; различающиеся варианты сохранены отдельно.
A3: ← К перечню тем
A5: Case Management в SOAR
A6: T-69C6C7C7 · Программы: РКИОК
A7: Вариант для: РКИОК
A8: Систематизация инцидентов: создание дел, назначение ответственных. Отслеживание статусов и результатов через встроенную систему управления делами. Интеграция с внешними сервис-десками и базами знаний.
A9: РКИОК — Реагирование на киберинциденты и отражение кибератак Раздел: Автоматизация обработки инцидентов · УТП: таблица 2, строка 60
A10: В программе: Тема 2. Case Management в SOAR (1 час лекции).
A11: Исходная программа РКИОК ↗ | D11: Исходный УТП РКИОК ↗
A12: =HYPERLINK("#'Выбор тем'!E"&MATCH("T-69C6C7C7",'Выбор тем'!$A:$A,0),"← Вернуться к теме")
A14: DoS- и DDoS-кибератаки
A15: T-22B750DE · Программы: ТК
A16: Вариант для: ТК
A17: DoS- и DDoS-кибератаки и их отличия. Виды DoS- и DDoS-кибератак. Классификация и цели DDoS-кибератак по уровням OSI. Атаки TCP-, UDP-, HTTP-flood. Способы защиты от DoS- и DDoS-кибератак.
A18: ТК — Технологии кибербезопасности: от spoofing-атак до VPN и межсетевых экранов Раздел: Практические аспекты обеспечения кибербезопасности корпоративных систем · УТП: таблица 2, строка 14
A19: В программе: Тема 2. DoS- и DDoS-кибератаки (2 часа лекции, 2 часа лабораторные занятия).
A20: Исходная программа ТК ↗ | D20: Исходный УТП ТК ↗
A21: =HYPERLINK("#'Выбор тем'!E"&MATCH("T-22B750DE",'Выбор тем'!$A:$A,0),"← Вернуться к теме")
A23: Internet of Things (IoT): архитектура, протоколы
A24: T-2AF2EE0F · Программы: ОПКС
A25: Вариант для: ОПКС
A26: Основные функции Internet of Things (IоT). Топология IoT, основные элементы, их функции. Процесс взаимодействия между сенсорными узлами (датчиками). Взаимодействие сервера IoT с приложением пользователя.
A27: ОПКС — Основы построения компьютерных сетей и обеспечения кибербезопасности Раздел: Основы построения компьютерных сетей · УТП: таблица 2, строка 16
A28: В программе: Тема 11. Internet of Things (IoT): архитектура, протоколы (2 часа лекции, 2 часа лабораторные занятия).
A29: Исходная программа ОПКС ↗ | D29: Исходный УТП ОПКС ↗
A30: =HYPERLINK("#'Выбор тем'!E"&MATCH("T-2AF2EE0F",'Выбор тем'!$A:$A,0),"← Вернуться к теме")
A32: IP-адресация
A33: T-33E76F66 · Программы: ОКМ
A34: Вариант для: ОКМ
A35: Структура IPv4- и IPv6-адресов. Представления IPv4- и IPv6-адресов в двоичной системе счисления. Определение адреса сети по IPv4-адресу и маске подсети. Определение сетевой и узловой части IPv4-адреса. Типы адресов IPv4- и IPv6-адресов. Отличие частных и публичных IPv4-адресов. Отличие классовой и бесклассовой IP-адресации. Бесклассовая IP-адресация. CIDR, VLSM. Принципы разбиения IPv4- и IPv6-сетей на подсети. Отличительные особенности разбиения на IPv4-сети и IPv6-сети.
A36: ОКМ — Основы обеспечения кибербезопасности. маршрутизация. IPv4- и IPv6-адресация Раздел: Маршрутизация. IPv4 и IPv6 адресация · УТП: таблица 2, строка 15
A37: В программе: Тема 1. IP-адресация (2 часа лекции, 2 часа лабораторные занятия).
A38: Исходная программа ОКМ ↗ | D38: Исходный УТП ОКМ ↗
A39: =HYPERLINK("#'Выбор тем'!E"&MATCH("T-33E76F66",'Выбор тем'!$A:$A,0),"← Вернуться к теме")
A41: OSINT-инструменты
A42: T-9917B01E · Программы: РКИОК
A43: Вариант для: РКИОК
A44: Понятие OSINT, его место в расследовании киберинцидентов. Типы источников данных. Основные категории OSINT-инструментов. Примеры использования OSINT при анализе инцидентов.
A45: РКИОК — Реагирование на киберинциденты и отражение кибератак Раздел: Введение в киберкриминалистику · УТП: таблица 2, строка 25
A46: В программе: Тема 5. OSINT-инструменты (1 час лекции).
A47: Исходная программа РКИОК ↗ | D47: Исходный УТП РКИОК ↗
A48: =HYPERLINK("#'Выбор тем'!E"&MATCH("T-9917B01E",'Выбор тем'!$A:$A,0),"← Вернуться к теме")
A50: SIEM: назначение, архитектура, нормализация и корреляция событий на базе Ntechnology SIEM
A51: T-B82746ED · Программы: РКИОК
A52: Вариант для: РКИОК
A53: Назначение SIEM в ЦКБ: сбор, хранение и анализ логов. Архитектура Ntechnology SIEM: источники, процессы нормализации. Принципы создания правил корреляции для выявления комплексных атак.
A54: РКИОК — Реагирование на киберинциденты и отражение кибератак Раздел: Сбор данных и предотвращение атак · УТП: таблица 2, строка 18
A55: В программе: Тема 4. SIEM: назначение, архитектура, нормализация и корреляция событий на базе Ntechnology SIEM (1 час лекции).
A56: Исходная программа РКИОК ↗ | D56: Исходный УТП РКИОК ↗
A57: =HYPERLINK("#'Выбор тем'!E"&MATCH("T-B82746ED",'Выбор тем'!$A:$A,0),"← Вернуться к теме")
A59: SIEM-системы. Краткий обзор существующих решений. Сертифицированные open-source и коммерческие решения в Республике Беларусь
A60: T-BF0DCE22 · Программы: ОКБО
A61: Вариант для: ОКБО
A62: Определение и основные компоненты SIEM-систем. Понятия и основные процессы, происходящие в SIEM-системах (идентификация источников, сбор, корреляция, агрегация, хранение и контроль защищенности). Рассмотрение примеров источников событий информационной безопасности и протоколов событий. Рассмотрение принципа работы SIEM-системы. Сравнительный анализ существующих решений в Республике Беларусь.
A63: ОКБО — Обеспечение кибербезопасности организаций Раздел: Системы управления информационной безопасностью и событиями безопасности (SIEM) · УТП: таблица 2, строка 28
A64: В программе: Тема 1. SIEM-системы. Краткий обзор существующих решений. Сертифицированные open-source и коммерческие решения в Республике Беларусь (2 часа лекции).
A65: Исходная программа ОКБО ↗ | D65: Исходный УТП ОКБО ↗
A66: =HYPERLINK("#'Выбор тем'!E"&MATCH("T-BF0DCE22",'Выбор тем'!$A:$A,0),"← Вернуться к теме")
A68: Suricata – установка, настройка, правила. Написание правил нормализации для Ntechnology SIEM (NTECH SIEM)
A69: T-2D7EF13A · Программы: РКИОК
A70: Вариант для: РКИОК
A71: Установка базового стенда. Запуск SIEM-системы. Развёртывание и конфигурирование Suricata в тестовой среде. Создание и тестирование собственных сигнатур для обнаружения атак. Разработка правил нормализации в Ntechnology SIEM для унификации событий.
A72: РКИОК — Реагирование на киберинциденты и отражение кибератак Раздел: Сбор данных и предотвращение атак · УТП: таблица 2, строка 19
A73: В программе: Тема 5. Suricata – установка, настройка, правила. Написание правил нормализации для Ntechnology SIEM (NTECH SIEM) (3 часа практические занятия).
A74: Исходная программа РКИОК ↗ | D74: Исходный УТП РКИОК ↗
A75: =HYPERLINK("#'Выбор тем'!E"&MATCH("T-2D7EF13A",'Выбор тем'!$A:$A,0),"← Вернуться к теме")
A77: Автоматизация и цифровизация административных процедур
A78: T-18B4A131 · Программы: ЦТГУ
A79: Вариант для: ЦТГУ
A80: Переход от регламента к цифровому процессу. Требования к данным и интеграциям (включая использование цифровых образов документов). Минимизация ручных операций; обеспечение прослеживаемости. Роль реестра административных процедур и конструктора электронных сервисов.
A81: ЦТГУ — Цифровая трансформация государственного управления Раздел: Нулевая бюрократия и клиентоцентричность · УТП: таблица 2, строка 14
A82: В программе: Тема 3. Автоматизация и цифровизация административных процедур (2 часа лекции).
A83: Исходная программа ЦТГУ ↗ | D83: Исходный УТП ЦТГУ ↗
A84: =HYPERLINK("#'Выбор тем'!E"&MATCH("T-18B4A131",'Выбор тем'!$A:$A,0),"← Вернуться к теме")
A86: Автоматизация процессов обеспечения кибербезопасности с использованием систем класса SGRC
A87: T-2C3B1F04 · Программы: ККС
A88: Вариант для: ККС
A89: Автоматизация процессов с использованием систем класса SGRC.
A90: Демонстрация возможностей систем класса SGRC (Security, Governance, Risk, Compliance) в части:
A91: автоматизации процесса инвентаризации и управления активами – идентификация всех активов, прорисовка связей между активами, определение ценности активов, составление реестра активов,
A92: автоматизации процесса проведения аудитов кибербезопасности;
A93: автоматизации процесса оценки рисков активов объектов информационной инфраструктуры.
A94: ККС — Кибербезопасность корпоративных систем Раздел: Технические меры по обеспечению кибербезопасности · УТП: таблица 2, строка 23
A95: В программе: Тема 9. Автоматизация процессов обеспечения кибербезопасности с использованием систем класса SGRC (4 часа практические занятия).
A96: Исходная программа ККС ↗ | D96: Исходный УТП ККС ↗
A97: =HYPERLINK("#'Выбор тем'!E"&MATCH("T-2C3B1F04",'Выбор тем'!$A:$A,0),"← Вернуться к теме")
A99: Агрегация каналов и отказоустойчивость: STP, LACP, балансировка
A100: T-E7C04975 · Программы: ОПКС
A101: Вариант для: ОПКС
A102: Назначение агрегирования каналов. Технологии и методы агрегации каналов, отличительные особенности. Петля коммутации, причины образования. Назначение протокола STP. Механизм работы STP протокола. Типы и содержание информации, которой обмениваются коммутаторы. Формат данных BPDU-кадра. Определение корневого коммутатора в автоматическом режиме работы протокола STP. Состояние и роли портов коммутатора. Отличие протоколов STP, PVST, PVST+, RSTP. Протокол LACP, механизм настройки и принцип работы. Отличительные особенности работы LACP и PAgP. Настройка протокола PAgP, особенности работы. Методы балансировки нагрузки, их настройка.
A103: ОПКС — Основы построения компьютерных сетей и обеспечения кибербезопасности Раздел: Основы построения компьютерных сетей · УТП: таблица 2, строка 10
A104: В программе: Тема 5. Агрегация каналов и отказоустойчивость: STP, LACP, балансировка (2 часа лекции, 2 часа лабораторные занятия).
A105: Исходная программа ОПКС ↗ | D105: Исходный УТП ОПКС ↗
A106: =HYPERLINK("#'Выбор тем'!E"&MATCH("T-E7C04975",'Выбор тем'!$A:$A,0),"← Вернуться к теме")
A108: Агрегация маршрутов
A109: T-DA2CB29B · Программы: ОКМ
A110: Вариант для: ОКМ
A111: Назначение агрегации маршрутов. Условия объединения IPv4- и IPv6-маршрутов. Принцип объединения IPv4-сетей в один адрес. Расчет суммарного статического IPv4-маршрута. Расчет суммарного IPv6-маршрута. Примеры реализации автоматического и административного суммирования IPv4- и IPv6-маршрутов. Назначение плавающих статических IPv4- и IPv6-маршрутов, принципы их конфигурации.
A112: ОКМ — Основы обеспечения кибербезопасности. маршрутизация. IPv4- и IPv6-адресация Раздел: Маршрутизация. IPv4 и IPv6 адресация · УТП: таблица 2, строка 23
...

Sheet Инструкция
A1: ИНСТРУКЦИЯ
A3: 1 · Сохраните свою копию
A4: Откройте файл в Excel или LibreOffice Calc. Предварительный просмотр в чате может не поддерживать редактирование.
A6: 2 · Представьтесь
A7: Укажите ФИО полностью. Дату можно не заполнять.
A9: 3 · Посмотрите содержание
A10: Нажмите «Открыть →» напротив темы. Если тема встречается в нескольких программах, изучите соответствующие варианты. Интернет для содержания не нужен.
A12: 4 · Отметьте готовность
A13: «Да» — готовы читать тему в приведённом объёме. «Частично» — есть ограничения по содержанию или программе: поясните их в комментарии. Пустая отметка означает «не указано», а не отказ.
A15: 5 · Завершите и отправьте
A16: Выберите «Выбор завершён», сохраните свою копию как «Анкета_Фамилия.xlsx» и отправьте организатору лично. В общий чат предназначен только пустой шаблон.
A18: Что находится в каталоге
... A22: Темы без отдельного описания и несовпадения программы с УТП помечены в карточках. В ПСАЭ часть тем входит в общий практикум. Подробности — в отчёте проверки источников у организатора.
